{
    "items": [ 
        {
            "type": "plugin", 
            "title": "Classic Musical Movies", 
            "link": "plugin.video.youtube/playlist/PL8Nn95jd6kYVouE2YjQT2oTwG7ZbAjak1", 
            "thumbnail": "", 
            "fanart": ""
        },         
        {
            "type": "plugin", 
            "title": "MUSICAL MOVIES FREE", 
            "link": "plugin.video.youtube/playlist/PLKDsBjdawnpZeu37KtB5DTGc6_V997Lem", 
            "thumbnail": "", 
            "fanart": ""
        },         
        {
            "type": "plugin", 
            "title": "Old Movies", 
            "link": "plugin.video.youtube/playlist/PL7Y-ri7Y2odOGaiH_ojno5aZIjjB7ADYi", 
            "thumbnail": "", 
            "fanart": ""
        },         
        {
            "type": "plugin", 
            "title": "Full Broadway Shows", 
            "link": "plugin.video.youtube/playlist/PL9kgdb7Eid2zvLXVlUFPJO57fXUzOglmQ", 
            "thumbnail": "", 
            "fanart": ""
        }, 
        {
            "type": "plugin", 
            "title": "BONUS VERY OLD MOVIES OF ALL SORTS (Mainly B&W)", 
            "link": "plugin.video.youtube/playlist/PLX9_I-EOJPdFuOjcI2zkmTck55homHEBE", 
            "thumbnail": "", 
            "fanart": ""
        },             
        {
            "type": "plugin", 
            "title": "Bonus TV Movies: 70s, 80s, 90s & 2000s", 
            "link": "plugin.video.youtube/playlist/PLdV_8CaQ81OAHpmtv7gN0iBDG92iHI9lN", 
            "thumbnail": "", 
            "fanart": ""
        } 
    ]
}
