{
    "items": [    
        {
            "fanart": "https://creamfields.com/wp-content/uploads/2025/08/ARC_FIRE-1600x900.jpg", 
            "link": [
                "https://youtu.be/xZxRlPqum3Y( STEEL YARD Day 1 )", 
                "https://youtu.be/OXfurfcYm4M( HALO Day 1 )"
            ], 
            "thumbnail": "https://images.ctfassets.net/bffxiku554r1/1XQMrQByGHpXDXr6xUbJMC/3d9049ebe15cd63c4fe6abd57073c632/Creamfields_2025.png?fm=png", 
            "title": "Creamfields 2025 Live", 
            "type": "item"
        }         
        {
            "type": "plugin", 
            "title": "Creamfields 2024", 
            "link": "plugin.video.youtube/playlist/PL7mkH1L93DlI5vvWd22Rvwm9kLJa49wFQ", 
            "thumbnail": "https://i.ytimg.com/vi/GJ75F_MdJYc/hqdefault.jpg", 
            "fanart": "https://github.com/MetalDudesMusic/pics/blob/main/PTFM%20BG%201080p.png?raw=true"
        },           
        {
            "type": "plugin", 
            "title": "Creamfields 2023", 
            "link": "plugin.video.youtube/playlist/PL7mkH1L93DlJWovBBX4Eoeo8gY-nZPhBa", 
            "thumbnail": "https://www.thefestivalcalendar.co.uk/images/thumbs/creamfields-north.jpg", 
            "fanart": "https://github.com/MetalDudesMusic/pics/blob/main/PTFM%20BG%201080p.png?raw=true"
        },            
        {
            "type": "plugin", 
            "title": "Creamfields North 2022", 
            "link": "plugin.video.youtube/playlist/PL7mkH1L93DlI0zWj3gJaDXa92GSeVj-wo", 
            "thumbnail": "https://www.jollygreensherpas.com/wp-content/uploads/2021/05/creamfields-2022-cover-twitter-840x430.jpeg", 
            "fanart": "https://github.com/MetalDudesMusic/pics/blob/main/PTFM%20BG%201080p.png?raw=true"
        },            
        {
            "type": "plugin", 
            "title": "Creamfields North 2019", 
            "link": "plugin.video.youtube/playlist/PL7mkH1L93DlJyUDoT3HMtgvDZty1Jjnrl", 
            "thumbnail": "https://i0.wp.com/worlddjfestivals.com/wp-content/uploads/2019/03/08-22-19-Creamfields-2019-cover.jpg", 
            "fanart": "https://github.com/MetalDudesMusic/pics/blob/main/PTFM%20BG%201080p.png?raw=true"
        }
    ]
}

